experimental.gracefulblobmissing-2.0-py3.11-nspkg.pth
experimental/gracefulblobmissing/__init__.py
experimental/gracefulblobmissing/configure.zcml
experimental/gracefulblobmissing/patches.py
experimental/gracefulblobmissing/tests.py
experimental/gracefulblobmissing/dummies/blob.png
experimental.gracefulblobmissing-2.0.dist-info/METADATA
experimental.gracefulblobmissing-2.0.dist-info/WHEEL
experimental.gracefulblobmissing-2.0.dist-info/entry_points.txt
experimental.gracefulblobmissing-2.0.dist-info/namespace_packages.txt
experimental.gracefulblobmissing-2.0.dist-info/top_level.txt
experimental.gracefulblobmissing-2.0.dist-info/RECORD
