Metadata-Version: 2.1
Name: experimental.gracefulblobmissing
Version: 2.0
Summary: Patch for Plone. Don't raise errors for file contents with missing BLOB file
Home-page: http://plone.org/products/experimental.gracefulblobmissing
Author: RedTurtle Technology
Author-email: sviluppoplone@redturtle.it
License: GPL
Keywords: plone blob patch
Classifier: Framework :: Plone
Classifier: Framework :: Plone :: 5.1
Classifier: Framework :: Plone :: 5.2
Classifier: License :: OSI Approved :: GNU General Public License v2 (GPLv2)
Classifier: Programming Language :: Python
Classifier: Development Status :: 4 - Beta
Classifier: Programming Language :: Python
Classifier: Programming Language :: Python :: 2.7
Classifier: Programming Language :: Python :: 3.6
Classifier: Programming Language :: Python :: 3.7
Classifier: Programming Language :: Python :: 3.8
Classifier: Programming Language :: Python :: 3.9
Requires-Dist: setuptools
Requires-Dist: collective.monkeypatcher (>=1.0)
